mstrio/__init__.py
mstrio/config.py
mstrio/connection.py
mstrio/helpers.py
mstrio/types.py
mstrio/access_and_security/__init__.py
mstrio/access_and_security/privilege.py
mstrio/access_and_security/privilege_mode.py
mstrio/access_and_security/security_role.py
mstrio/api/__init__.py
mstrio/api/administration.py
mstrio/api/applications.py
mstrio/api/attributes.py
mstrio/api/authentication.py
mstrio/api/bookmarks.py
mstrio/api/browsing.py
mstrio/api/calendars.py
mstrio/api/change_journal.py
mstrio/api/changesets.py
mstrio/api/contact_groups.py
mstrio/api/contacts.py
mstrio/api/content_groups.py
mstrio/api/cubes.py
mstrio/api/custom_groups.py
mstrio/api/datasets.py
mstrio/api/datasources.py
mstrio/api/devices.py
mstrio/api/documents.py
mstrio/api/drivers.py
mstrio/api/emails.py
mstrio/api/events.py
mstrio/api/facts.py
mstrio/api/filters.py
mstrio/api/folders.py
mstrio/api/gateways.py
mstrio/api/hierarchies.py
mstrio/api/hooks.py
mstrio/api/incremental_refresh_reports.py
mstrio/api/languages.py
mstrio/api/library.py
mstrio/api/license.py
mstrio/api/metrics.py
mstrio/api/migration.py
mstrio/api/misc.py
mstrio/api/monitors.py
mstrio/api/objects.py
mstrio/api/palettes.py
mstrio/api/projects.py
mstrio/api/prompts.py
mstrio/api/registrations.py
mstrio/api/reports.py
mstrio/api/runtimes.py
mstrio/api/schedules.py
mstrio/api/schema.py
mstrio/api/scripts.py
mstrio/api/security.py
mstrio/api/security_filters.py
mstrio/api/subscriptions.py
mstrio/api/tables.py
mstrio/api/timezones.py
mstrio/api/transformations.py
mstrio/api/transmitters.py
mstrio/api/user_hierarchies.py
mstrio/api/usergroups.py
mstrio/api/users.py
mstrio/datasources/__init__.py
mstrio/datasources/database_connections.py
mstrio/datasources/datasource_connection.py
mstrio/datasources/datasource_instance.py
mstrio/datasources/datasource_login.py
mstrio/datasources/datasource_map.py
mstrio/datasources/dbms.py
mstrio/datasources/driver.py
mstrio/datasources/embedded_connection.py
mstrio/datasources/gateway.py
mstrio_py-11.5.12.101.dist-info/METADATA
mstrio_py-11.5.12.101.dist-info/WHEEL
mstrio_py-11.5.12.101.dist-info/RECORD
