Metadata-Version: 2.4
Name: mstrio-py
Version: 11.5.12.101
Summary: Python interface for the Strategy One REST API
Project-URL: Bug Tracker, https://github.com/MicroStrategy/mstrio-py/issues
Project-URL: Documentation, https://www2.microstrategy.com/producthelp/Current/mstrio-py/
Project-URL: Source Code, https://github.com/MicroStrategy/mstrio-py
Project-URL: Quick Manual, https://www2.microstrategy.com/producthelp/Current/Workstation/en-us/Content/intro_scripts.htm
Author-email: Strategy One <bkaczynski@strategy.com>
License-Expression: LicenseRef-Proprietary
Classifier: Intended Audience :: End Users/Desktop
Classifier: Intended Audience :: Science/Research
Classifier: Intended Audience :: System Administrators
Classifier: Natural Language :: English
Classifier: Operating System :: OS Independent
Classifier: Programming Language :: Python
Classifier: Programming Language :: Python :: 3
Classifier: Programming Language :: Python :: 3 :: Only
Classifier: Programming Language :: Python :: 3.10
Classifier: Programming Language :: Python :: 3.11
Classifier: Programming Language :: Python :: 3.12
Classifier: Programming Language :: Python :: 3.13
Classifier: Topic :: Scientific/Engineering
Classifier: Topic :: Software Development
Classifier: Topic :: Software Development :: Libraries
Requires-Python: <3.14,>=3.10
Requires-Dist: packaging>=24.2
Requires-Dist: pandas[output-formatting,pyarrow]>=1.1.5
Requires-Dist: pyhumps>=3.8
Requires-Dist: pypika>=0.48.9
Requires-Dist: requests-futures>=1
Requires-Dist: requests>=2.32.3
Requires-Dist: stringcase>=1.2
Requires-Dist: tqdm>=4.66.4
Provides-Extra: all
Requires-Dist: black; extra == 'all'
Requires-Dist: codespell; extra == 'all'
Requires-Dist: coverage; extra == 'all'
Requires-Dist: enum-tools[sphinx]; extra == 'all'
Requires-Dist: flake8; extra == 'all'
Requires-Dist: flake8-black; extra == 'all'
Requires-Dist: flaky; extra == 'all'
Requires-Dist: isort; extra == 'all'
Requires-Dist: m2r2; extra == 'all'
Requires-Dist: mistune; extra == 'all'
Requires-Dist: mypy; extra == 'all'
Requires-Dist: nose; extra == 'all'
Requires-Dist: notebook; extra == 'all'
Requires-Dist: pipdeptree; extra == 'all'
Requires-Dist: pre-commit; extra == 'all'
Requires-Dist: pytest; extra == 'all'
Requires-Dist: pytest-cov; extra == 'all'
Requires-Dist: python-decouple; extra == 'all'
Requires-Dist: python-dotenv[cli]; extra == 'all'
Requires-Dist: recommonmark; extra == 'all'
Requires-Dist: sphinx; extra == 'all'
Requires-Dist: tox; extra == 'all'
Requires-Dist: yapf; extra == 'all'
Provides-Extra: config
Requires-Dist: pipdeptree; extra == 'config'
Provides-Extra: dev
Requires-Dist: black; extra == 'dev'
Requires-Dist: codespell; extra == 'dev'
Requires-Dist: coverage; extra == 'dev'
Requires-Dist: flake8; extra == 'dev'
Requires-Dist: flake8-black; extra == 'dev'
Requires-Dist: flaky; extra == 'dev'
Requires-Dist: isort; extra == 'dev'
Requires-Dist: mypy; extra == 'dev'
Requires-Dist: nose; extra == 'dev'
Requires-Dist: pre-commit; extra == 'dev'
Requires-Dist: pytest; extra == 'dev'
Requires-Dist: pytest-cov; extra == 'dev'
Requires-Dist: python-decouple; extra == 'dev'
Requires-Dist: python-dotenv[cli]; extra == 'dev'
Requires-Dist: tox; extra == 'dev'
Requires-Dist: yapf; extra == 'dev'
Provides-Extra: docs
Requires-Dist: enum-tools[sphinx]; extra == 'docs'
Requires-Dist: m2r2; extra == 'docs'
Requires-Dist: mistune; extra == 'docs'
Requires-Dist: recommonmark; extra == 'docs'
Requires-Dist: sphinx; extra == 'docs'
Provides-Extra: jupyter
Requires-Dist: notebook; extra == 'jupyter'
Provides-Extra: lint
Requires-Dist: black; extra == 'lint'
Requires-Dist: flake8; extra == 'lint'
Requires-Dist: flake8-black; extra == 'lint'
Requires-Dist: yapf; extra == 'lint'
Provides-Extra: pre-commit
Requires-Dist: codespell; extra == 'pre-commit'
Requires-Dist: isort; extra == 'pre-commit'
Requires-Dist: pre-commit; extra == 'pre-commit'
Provides-Extra: strict
Requires-Dist: jinja2>=3.1.5; extra == 'strict'
Requires-Dist: numpy>=2; extra == 'strict'
Requires-Dist: packaging>=24.2; extra == 'strict'
Requires-Dist: pandas[output-formatting,pyarrow]>=2; extra == 'strict'
Requires-Dist: pyarrow>=19; extra == 'strict'
Requires-Dist: pyhumps>=3.8; extra == 'strict'
Requires-Dist: pypika>=0.48.9; extra == 'strict'
Requires-Dist: requests-futures>=1; extra == 'strict'
Requires-Dist: requests>=2.32.3; extra == 'strict'
Requires-Dist: stringcase>=1.2; extra == 'strict'
Requires-Dist: tox>=4.23.2; extra == 'strict'
Requires-Dist: tqdm>=4.66.4; extra == 'strict'
Requires-Dist: urllib3>=2; extra == 'strict'
Provides-Extra: test
Requires-Dist: coverage; extra == 'test'
Requires-Dist: flaky; extra == 'test'
Requires-Dist: nose; extra == 'test'
Requires-Dist: pytest; extra == 'test'
Requires-Dist: pytest-cov; extra == 'test'
Requires-Dist: python-decouple; extra == 'test'
